{"stats":{"minecraft:killed_by":{"minecraft:creeper":3,"minecraft:pillager":1,"minecraft:drowned":1,"minecraft:witch":1},"minecraft:mined":{"minecraft:cobblestone_stairs":18,"minecraft:carved_pumpkin":1,"minecraft:obsidian":6,"minecraft:granite":189,"minecraft:acacia_log":155,"minecraft:grass_block":299,"minecraft:composter":2,"minecraft:hopper":3,"minecraft:acacia_pressure_plate":1,"minecraft:oxeye_daisy":1,"minecraft:magma_block":1,"minecraft:dark_oak_trapdoor":11,"minecraft:iron_ore":339,"minecraft:barrel":1,"minecraft:pumpkin":80,"minecraft:blue_orchid":1,"minecraft:cut_sandstone":4,"minecraft:kelp_plant":1,"minecraft:torch":52,"minecraft:poppy":3,"minecraft:chest":5,"minecraft:cobblestone":36,"minecraft:sugar_cane":186,"minecraft:wall_torch":45,"minecraft:seagrass":1,"minecraft:acacia_sapling":1,"minecraft:wheat":397,"minecraft:grass":178,"minecraft:oak_log":49,"minecraft:acacia_fence":12,"minecraft:sand":11,"minecraft:dirt":203,"minecraft:stonecutter":1,"minecraft:oak_leaves":17,"minecraft:diamond_ore":33,"minecraft:mossy_cobblestone":2,"minecraft:sea_lantern":1,"minecraft:kelp":2,"minecraft:hay_block":1,"minecraft:redstone_ore":172,"minecraft:carrots":64,"minecraft:acacia_trapdoor":1,"minecraft:snow":35,"minecraft:andesite":186,"minecraft:lantern":2,"minecraft:bamboo_sapling":1,"minecraft:bamboo":117,"minecraft:stone":3629,"minecraft:oak_slab":1,"minecraft:acacia_leaves":32,"minecraft:scaffolding":7,"minecraft:lily_of_the_valley":1,"minecraft:dandelion":1,"minecraft:crafting_table":1,"minecraft:emerald_ore":1,"minecraft:campfire":1,"minecraft:lapis_ore":26,"minecraft:diorite":208,"minecraft:spruce_stairs":3,"minecraft:acacia_fence_gate":2,"minecraft:white_carpet":2,"minecraft:spruce_log":2,"minecraft:birch_leaves":1,"minecraft:bee_nest":1,"minecraft:coal_ore":929,"minecraft:gravel":84,"minecraft:gold_ore":47},"minecraft:dropped":{"minecraft:leather_helmet":1,"minecraft:cut_sandstone":2,"minecraft:sand":1,"minecraft:iron_pickaxe":1,"minecraft:wheat":2,"minecraft:rotten_flesh":5,"minecraft:leather_chestplate":1,"minecraft:oak_slab":1,"minecraft:wheat_seeds":19,"minecraft:feather":4,"minecraft:lily_pad":47,"minecraft:bowl":1,"minecraft:lily_of_the_valley":1,"minecraft:andesite":1,"minecraft:blue_orchid":2},"minecraft:crafted":{"minecraft:oak_planks":148,"minecraft:barrel":4,"minecraft:acacia_pressure_plate":4,"minecraft:stone":3,"minecraft:bookshelf":15,"minecraft:hopper":9,"minecraft:iron_boots":1,"minecraft:chest":11,"minecraft:acacia_fence":99,"minecraft:stone_hoe":3,"minecraft:smoker":1,"minecraft:item_frame":1,"minecraft:oak_slab":12,"minecraft:wooden_shovel":1,"minecraft:acacia_wood":6,"minecraft:arrow":40,"minecraft:cooked_porkchop":5,"minecraft:map":1,"minecraft:crafting_table":1,"minecraft:acacia_slab":12,"minecraft:iron_helmet":1,"minecraft:hay_block":1,"minecraft:pumpkin_seeds":4,"minecraft:campfire":2,"minecraft:cartography_table":1,"minecraft:iron_chestplate":1,"minecraft:book":51,"minecraft:paper":165,"minecraft:diamond_pickaxe":1,"minecraft:yellow_dye":1,"minecraft:shield":6,"minecraft:stick":280,"minecraft:iron_ingot":12,"minecraft:compass":3,"minecraft:iron_pickaxe":7,"minecraft:iron_block":17,"minecraft:stone_sword":1,"minecraft:snow_block":8,"minecraft:acacia_door":3,"minecraft:light_gray_dye":1,"minecraft:composter":1,"minecraft:shears":1,"minecraft:stone_shovel":2,"minecraft:fishing_rod":3,"minecraft:tripwire_hook":2,"minecraft:iron_nugget":9,"minecraft:furnace":2,"minecraft:acacia_fence_gate":4,"minecraft:jack_o_lantern":1,"minecraft:white_carpet":6,"minecraft:scaffolding":84,"minecraft:lantern":1,"minecraft:iron_axe":3,"minecraft:ladder":6,"minecraft:stone_pickaxe":20,"minecraft:redstone_block":89,"minecraft:coal_block":88,"minecraft:sugar":17,"minecraft:red_dye":2,"minecraft:crossbow":1,"minecraft:diamond_sword":1,"minecraft:enchanting_table":1,"minecraft:iron_sword":1,"minecraft:acacia_trapdoor":2,"minecraft:cooked_salmon":1,"minecraft:bucket":3,"minecraft:stone_axe":1,"minecraft:bread":66,"minecraft:air":0,"minecraft:oak_fence_gate":1,"minecraft:oak_boat":1,"minecraft:iron_shovel":2,"minecraft:iron_leggings":1,"minecraft:stonecutter":1,"minecraft:anvil":1,"minecraft:white_bed":1,"minecraft:pumpkin_pie":17,"minecraft:acacia_planks":400,"minecraft:torch":468,"minecraft:lapis_lazuli":18,"minecraft:lapis_block":19},"minecraft:broken":{"minecraft:iron_shovel":1,"minecraft:wooden_shovel":1,"minecraft:stone_pickaxe":19,"minecraft:stone_axe":1,"minecraft:wooden_axe":1,"minecraft:fishing_rod":1,"minecraft:stone_shovel":2,"minecraft:stone_sword":1,"minecraft:stone_hoe":1,"minecraft:shield":2,"minecraft:iron_axe":2,"minecraft:leather_boots":2,"minecraft:iron_pickaxe":5},"minecraft:custom":{"minecraft:animals_bred":126,"minecraft:interact_with_crafting_table":262,"minecraft:open_barrel":176,"minecraft:leave_game":37,"minecraft:time_since_death":140502,"minecraft:sprint_one_cm":1276296,"minecraft:damage_blocked_by_shield":8585,"minecraft:drop":23,"minecraft:talked_to_villager":7,"minecraft:deaths":14,"minecraft:jump":7928,"minecraft:walk_on_water_one_cm":73552,"minecraft:enchant_item":4,"minecraft:interact_with_furnace":55,"minecraft:interact_with_cartography_table":7,"minecraft:play_one_minute":984648,"minecraft:sleep_in_bed":41,"minecraft:damage_dealt":31824,"minecraft:crouch_one_cm":51921,"minecraft:interact_with_smoker":4,"minecraft:horse_one_cm":304,"minecraft:mob_kills":283,"minecraft:interact_with_anvil":6,"minecraft:inspect_hopper":92,"minecraft:climb_one_cm":90461,"minecraft:walk_one_cm":3572629,"minecraft:sneak_time":19534,"minecraft:walk_under_water_one_cm":52787,"minecraft:boat_one_cm":394762,"minecraft:interact_with_stonecutter":9,"minecraft:time_since_rest":14691,"minecraft:damage_taken":5927,"minecraft:swim_one_cm":55601,"minecraft:fly_one_cm":1731665,"minecraft:open_chest":484,"minecraft:fish_caught":134,"minecraft:fall_one_cm":168621},"minecraft:picked_up":{"minecraft:wheat":685,"minecraft:suspicious_stew":2,"minecraft:yellow_wool":4,"minecraft:lead":11,"minecraft:acacia_pressure_plate":2,"minecraft:potion":1,"minecraft:enchanted_book":1,"minecraft:lapis_block":17,"minecraft:string":20,"minecraft:dark_oak_trapdoor":11,"minecraft:pufferfish":19,"minecraft:acacia_fence_gate":2,"minecraft:iron_pickaxe":1,"minecraft:stick":62,"minecraft:acacia_fence":12,"minecraft:composter":2,"minecraft:acacia_log":155,"minecraft:torch":162,"minecraft:spruce_stairs":3,"minecraft:porkchop":20,"minecraft:diorite":206,"minecraft:rotten_flesh":74,"minecraft:tropical_fish":4,"minecraft:carved_pumpkin":1,"minecraft:obsidian":6,"minecraft:cod":75,"minecraft:snowball":35,"minecraft:cobblestone":3660,"minecraft:magma_block":1,"minecraft:leather_chestplate":2,"minecraft:feather":11,"minecraft:water_bucket":1,"minecraft:andesite":184,"minecraft:brown_wool":6,"minecraft:golden_leggings":1,"minecraft:flint":11,"minecraft:light_gray_dye":1,"minecraft:lantern":2,"minecraft:lapis_lazuli":164,"minecraft:dirt":549,"minecraft:leather_boots":4,"minecraft:bone":26,"minecraft:stonecutter":1,"minecraft:bow":3,"minecraft:wheat_seeds":1603,"minecraft:bamboo":1097,"minecraft:oak_planks":8,"minecraft:cooked_porkchop":2,"minecraft:sand":23,"minecraft:lily_of_the_valley":1,"minecraft:barrel":1,"minecraft:mossy_cobblestone":2,"minecraft:diamond":41,"minecraft:crossbow":1,"minecraft:granite":187,"minecraft:bone_meal":28,"minecraft:bread":1,"minecraft:emerald":1,"minecraft:oak_sapling":13,"minecraft:fishing_rod":1,"minecraft:charcoal":2,"minecraft:crafting_table":1,"minecraft:chicken":5,"minecraft:wooden_pickaxe":1,"minecraft:pink_wool":4,"minecraft:white_carpet":2,"minecraft:blue_orchid":2,"minecraft:beef":108,"minecraft:oak_boat":6,"minecraft:iron_nugget":10,"minecraft:poppy":12,"minecraft:light_gray_wool":12,"minecraft:sugar_cane":304,"minecraft:chest":5,"minecraft:egg":3,"minecraft:bowl":1,"minecraft:carrot":229,"minecraft:redstone":809,"minecraft:prismarine_crystals":3,"minecraft:arrow":28,"minecraft:hay_block":1,"minecraft:saddle":1,"minecraft:mutton":53,"minecraft:white_wool":30,"minecraft:oxeye_daisy":1,"minecraft:salmon":47,"minecraft:cut_sandstone":2,"minecraft:leather":53,"minecraft:oak_log":49,"minecraft:lily_pad":48,"minecraft:gunpowder":20,"minecraft:cobblestone_stairs":18,"minecraft:white_banner":2,"minecraft:apple":5,"minecraft:kelp":4,"minecraft:acacia_trapdoor":1,"minecraft:iron_ingot":10,"minecraft:iron_ore":337,"minecraft:acacia_sapling":30,"minecraft:scaffolding":37,"minecraft:oak_slab":1,"minecraft:pumpkin":79,"minecraft:red_wool":2,"minecraft:dandelion":1,"minecraft:gravel":77,"minecraft:spruce_log":2,"minecraft:gold_ore":50,"minecraft:spider_eye":5,"minecraft:leather_helmet":1,"minecraft:pumpkin_seeds":4,"minecraft:gray_wool":10,"minecraft:black_wool":5,"minecraft:coal":1248,"minecraft:hopper":3},"minecraft:killed":{"minecraft:spider":17,"minecraft:skeleton":19,"minecraft:chicken":43,"minecraft:pig":10,"minecraft:zombie_villager":1,"minecraft:salmon":5,"minecraft:creeper":16,"minecraft:sheep":38,"minecraft:pillager":9,"minecraft:zombie":68,"minecraft:cow":53,"minecraft:drowned":1},"minecraft:used":{"minecraft:iron_shovel":283,"minecraft:poppy":1,"minecraft:ladder":6,"minecraft:chest":7,"minecraft:stone":285,"minecraft:iron_sword":329,"minecraft:carrot":119,"minecraft:acacia_sapling":27,"minecraft:glass":7,"minecraft:lantern":3,"minecraft:item_frame":1,"minecraft:bow":47,"minecraft:hay_block":2,"minecraft:scaffolding":117,"minecraft:furnace":1,"minecraft:oak_sapling":10,"minecraft:acacia_fence":110,"minecraft:egg":126,"minecraft:diorite":29,"minecraft:acacia_trapdoor":3,"minecraft:stone_pickaxe":2626,"minecraft:wooden_pickaxe":3,"minecraft:composter":3,"minecraft:sugar_cane":74,"minecraft:crossbow":4,"minecraft:pumpkin_seeds":4,"minecraft:acacia_door":3,"minecraft:bread":67,"minecraft:diamond_sword":6,"minecraft:andesite":21,"minecraft:oak_boat":7,"minecraft:enchanting_table":1,"minecraft:stone_sword":158,"minecraft:acacia_log":8,"minecraft:stone_shovel":277,"minecraft:wooden_shovel":59,"minecraft:cooked_salmon":5,"minecraft:stone_hoe":158,"minecraft:cooked_chicken":11,"minecraft:torch":487,"minecraft:dirt":192,"minecraft:anvil":2,"minecraft:white_carpet":8,"minecraft:hopper":12,"minecraft:granite":28,"minecraft:oak_fence_gate":1,"minecraft:wooden_axe":56,"minecraft:bookshelf":15,"minecraft:iron_axe":578,"minecraft:barrel":5,"minecraft:bamboo":40,"minecraft:pumpkin":2,"minecraft:wheat_seeds":674,"minecraft:water_bucket":18,"minecraft:cobblestone_stairs":145,"minecraft:cartography_table":1,"minecraft:stonecutter":2,"minecraft:oak_slab":1,"minecraft:crafting_table":2,"minecraft:white_bed":1,"minecraft:campfire":2,"minecraft:spruce_log":2,"minecraft:smoker":1,"minecraft:diamond_pickaxe":1501,"minecraft:apple":5,"minecraft:iron_pickaxe":1736,"minecraft:suspicious_stew":2,"minecraft:map":1,"minecraft:acacia_fence_gate":6,"minecraft:stone_axe":105,"minecraft:fishing_rod":174,"minecraft:cobblestone":492,"minecraft:acacia_pressure_plate":5,"minecraft:cooked_porkchop":11,"minecraft:bucket":20,"minecraft:pumpkin_pie":17}},"DataVersion":2230}